zip_analyzer/__init__.py
zip_analyzer/cli_script.py
zip_analyzer/password_list.txt
zip_analyzer-1.0.0.dist-info/LICENSE
zip_analyzer-1.0.0.dist-info/METADATA
zip_analyzer-1.0.0.dist-info/WHEEL
zip_analyzer-1.0.0.dist-info/entry_points.txt
zip_analyzer-1.0.0.dist-info/top_level.txt
zip_analyzer-1.0.0.dist-info/RECORD
