Metadata-Version: 2.1
Name: zip-analyzer
Version: 1.0.0
Summary: A cli script to analyze zip archive.
Home-page: https://github.com/wahlflo/zip_analyzer
Author: Florian Wahl
Author-email: florian.wahl.developer@gmail.com
License: UNKNOWN
Platform: UNKNOWN
Classifier: Programming Language :: Python :: 3
Classifier: License :: OSI Approved :: MIT License
Classifier: Operating System :: OS Independent
Requires-Dist: cli-formatter (>=1.2.0)
Requires-Dist: zipfile37
